gymnasium_cartpole_swingup/__init__.py
gymnasium_cartpole_swingup/cartpole_swingup.py
gymnasium_cartpole_swingup-0.1.8.dist-info/licenses/LICENSE
gymnasium_cartpole_swingup-0.1.8.dist-info/METADATA
gymnasium_cartpole_swingup-0.1.8.dist-info/WHEEL
gymnasium_cartpole_swingup-0.1.8.dist-info/top_level.txt
gymnasium_cartpole_swingup-0.1.8.dist-info/RECORD
