Metadata-Version: 2.4
Name: gymnasium-cartpole-swingup
Version: 0.1.8
Summary: CartPole SwingUp environment for Gymnasium
Author-email: Naoki Kiyohara <n.kiyohara23@imperial.ac.uk>
License: MIT
Project-URL: Homepage, https://github.com/nkiyohara/gymnasium-cartpole-swingup
Project-URL: Issues, https://github.com/nkiyohara/gymnasium-cartpole-swingup/issues
Keywords: reinforcement-learning,gymnasium,cartpole,swing-up
Classifier: Development Status :: 4 - Beta
Classifier: Intended Audience :: Science/Research
Classifier: License :: OSI Approved :: MIT License
Classifier: Programming Language :: Python :: 3
Classifier: Programming Language :: Python :: 3.8
Classifier: Programming Language :: Python :: 3.9
Classifier: Programming Language :: Python :: 3.10
Classifier: Programming Language :: Python :: 3.11
Classifier: Programming Language :: Python :: 3.12
Classifier: Programming Language :: Python :: 3.13
Classifier: Topic :: Scientific/Engineering :: Artificial Intelligence
Requires-Python: >=3.8
License-File: LICENSE
Requires-Dist: gymnasium>=1.0.0
Requires-Dist: numpy>=1.18.0
Requires-Dist: pygame>=2.1.0
Dynamic: license-file
